{
  "brand": "PRAXIS",
  "version": "1.0",
  "direction": "02 Glasswork",
  "color": {
    "velvet": {
      "value": "#0B0717",
      "comment": "Primary surface — 70% of any screen"
    },
    "surface": {
      "value": "#150D26",
      "comment": "Cards, raised UI — 15%"
    },
    "ink": {
      "value": "#F5F1FF",
      "comment": "Headlines, stat values"
    },
    "ink-soft": {
      "value": "#D7CFEC",
      "comment": "Body copy on dark"
    },
    "mute": {
      "value": "#A89DC8",
      "comment": "Labels, mono, secondary"
    },
    "hairline": {
      "value": "rgba(255,255,255,0.08)",
      "comment": "1px borders"
    },
    "cyan": {
      "value": "#3DE8E0",
      "comment": "System voice, gradient L"
    },
    "pink": {
      "value": "#FF5BB0",
      "comment": "Energy, gradient R"
    },
    "gold": {
      "value": "#F4C557",
      "comment": "Loot, value, ceremony"
    },
    "amber": {
      "value": "#FFB347",
      "comment": "XP gain, warning soft"
    },
    "good": {
      "value": "#5BE38E",
      "comment": "Streaks, positive only"
    },
    "danger": {
      "value": "#FF4D6D",
      "comment": "HP loss, destructive"
    }
  },
  "gradient": {
    "system": {
      "value": "linear-gradient(135deg, #3DE8E0, #FF5BB0)",
      "degrees": 135
    },
    "gold": {
      "value": "linear-gradient(135deg, #FFE08A, #F4C557)",
      "degrees": 135
    }
  },
  "typography": {
    "display": {
      "family": "Space Grotesk",
      "weight": 600,
      "tracking": "-2.5%"
    },
    "body": {
      "family": "Inter Tight",
      "weight": 400
    },
    "mono": {
      "family": "JetBrains Mono",
      "weight": 500,
      "tracking": "+200"
    }
  },
  "radius": {
    "card": 18,
    "icon": "22.5%",
    "pill": 999
  }
}